MANIFEST.in
commands.py
description.txt
example_decorators.py
example_lazyargs.py
license.txt
setup.cfg
setup.py
lazyargs/__init__.py
lazyargs/api.py
lazyargs/args.py
lazyargs/decorate.py
lazyargs/errorhandler.py
lazyargs/functions.py
lazyargs/test.py
lazyargs/version.txt
lazyargs.egg-info/PKG-INFO
lazyargs.egg-info/SOURCES.txt
lazyargs.egg-info/dependency_links.txt
lazyargs.egg-info/not-zip-safe
lazyargs.egg-info/requires.txt
lazyargs.egg-info/top_level.txt