Metadata-Version: 1.1
Name: lazyargs
Version: 0.1.2
Summary: Lazily evaluated function arguments
Home-page: https://github.com/chriscz/lazyargs
Author: Chris Coetzee
Author-email: chriscz93@gmail.com
License: Mozilla Public License 2.0 (MPL 2.0)
Platform: UNKNOWN
Classifier: Development Status :: 4 - Beta
Classifier: Environment :: Console
Classifier: License :: OSI Approved :: Mozilla Public License 2.0 (MPL 2.0)
Classifier: Topic :: Utilities
